{
  "lastUpdated": "2026-05-27T08:33:13.241Z",
  "sections": [
    "13",
    "14",
    "15"
  ],
  "games": {
    "1": {
      "id": 1,
      "label": "Tue, Jun 2, 2026 · 7:15 PM · vs Blue Jays",
      "url": "https://www.stubhub.com/atlanta-braves-atlanta-tickets-6-2-2026/event/159262126/",
      "listings": [
        {
          "section": "13",
          "row": "13",
          "price": 126
        },
        {
          "section": "13",
          "row": "12",
          "price": 128
        },
        {
          "section": "13",
          "row": "6",
          "price": 176
        },
        {
          "section": "14",
          "row": "6",
          "price": 193
        },
        {
          "section": "14",
          "row": "5",
          "price": 199
        },
        {
          "section": "13",
          "row": "5",
          "price": 231
        },
        {
          "section": "14",
          "row": "2",
          "price": 233
        },
        {
          "section": "14",
          "row": "3",
          "price": 252
        },
        {
          "section": "15",
          "row": "4",
          "price": 434
        },
        {
          "section": "15",
          "row": "3",
          "price": 461
        }
      ],
      "parkingListings": [
        {
          "lot": "29",
          "price": 55
        },
        {
          "lot": "29",
          "price": 322
        }
      ],
      "parkingPrice": 55
    },
    "2": {
      "id": 2,
      "label": "Wed, Jun 3, 2026 · 7:15 PM · vs Blue Jays",
      "url": "https://www.stubhub.com/atlanta-braves-atlanta-tickets-6-3-2026/event/159262127/",
      "listings": [
        {
          "section": "14",
          "row": "6",
          "price": 237
        },
        {
          "section": "13",
          "row": "12",
          "price": 241
        },
        {
          "section": "13",
          "row": "9",
          "price": 247
        },
        {
          "section": "13",
          "row": "10",
          "price": 247
        },
        {
          "section": "13",
          "row": "7",
          "price": 256
        },
        {
          "section": "13",
          "row": "3",
          "price": 261
        },
        {
          "section": "14",
          "row": "2",
          "price": 277
        },
        {
          "section": "14",
          "row": "3",
          "price": 288
        },
        {
          "section": "14",
          "row": "1",
          "price": 296
        },
        {
          "section": "15",
          "row": "4",
          "price": 383
        }
      ],
      "parkingListings": [
        {
          "lot": "29",
          "price": 58
        },
        {
          "lot": "29",
          "price": 71
        }
      ],
      "parkingPrice": 58
    },
    "3": {
      "id": 3,
      "label": "Thu, Jun 4, 2026 · 7:15 PM · vs Blue Jays",
      "url": "https://www.stubhub.com/atlanta-braves-atlanta-tickets-6-4-2026/event/159262128/",
      "listings": [
        {
          "section": "13",
          "row": "10",
          "price": 153
        },
        {
          "section": "13",
          "row": "12",
          "price": 153
        },
        {
          "section": "13",
          "row": "13",
          "price": 153
        },
        {
          "section": "13",
          "row": "5",
          "price": 155
        },
        {
          "section": "13",
          "row": "4",
          "price": 159
        },
        {
          "section": "13",
          "row": "3",
          "price": 188
        },
        {
          "section": "14",
          "row": "5",
          "price": 203
        },
        {
          "section": "13",
          "row": "2",
          "price": 208
        },
        {
          "section": "13",
          "row": "1",
          "price": 225
        },
        {
          "section": "14",
          "row": "2",
          "price": 238
        },
        {
          "section": "14",
          "row": "2",
          "price": 240
        },
        {
          "section": "15",
          "row": "3",
          "price": 274
        }
      ],
      "parkingListings": [
        {
          "lot": "29",
          "price": 40
        },
        {
          "lot": "29",
          "price": 46
        }
      ],
      "parkingPrice": 40
    },
    "4": {
      "id": 4,
      "label": "Fri, Jun 5, 2026 · 7:15 PM · vs Pirates",
      "url": "https://www.stubhub.com/atlanta-braves-atlanta-tickets-6-5-2026/event/159262129/",
      "listings": [
        {
          "section": "14",
          "row": "10",
          "price": 232
        },
        {
          "section": "13",
          "row": "13",
          "price": 253
        },
        {
          "section": "13",
          "row": "6",
          "price": 260
        },
        {
          "section": "13",
          "row": "9",
          "price": 260
        },
        {
          "section": "13",
          "row": "11",
          "price": 260
        },
        {
          "section": "13",
          "row": "12",
          "price": 260
        },
        {
          "section": "14",
          "row": "6",
          "price": 278
        },
        {
          "section": "14",
          "row": "5",
          "price": 285
        },
        {
          "section": "14",
          "row": "3",
          "price": 316
        },
        {
          "section": "15",
          "row": "4",
          "price": 329
        },
        {
          "section": "14",
          "row": "2",
          "price": 332
        },
        {
          "section": "15",
          "row": "2",
          "price": 345
        }
      ],
      "parkingListings": [
        {
          "lot": "29",
          "price": 60
        },
        {
          "lot": "29",
          "price": 67
        }
      ],
      "parkingPrice": 60
    },
    "5": {
      "id": 5,
      "label": "Sat, Jun 6, 2026 · 4:10 PM · vs Pirates",
      "url": "https://www.stubhub.com/atlanta-braves-atlanta-tickets-6-6-2026/event/159262130/",
      "listings": [
        {
          "section": "14",
          "row": "11",
          "price": 243
        },
        {
          "section": "14",
          "row": "10",
          "price": 248
        },
        {
          "section": "13",
          "row": "5",
          "price": 261
        },
        {
          "section": "14",
          "row": "6",
          "price": 296
        },
        {
          "section": "13",
          "row": "2",
          "price": 306
        },
        {
          "section": "14",
          "row": "3",
          "price": 324
        },
        {
          "section": "15",
          "row": "3",
          "price": 343
        },
        {
          "section": "14",
          "row": "2",
          "price": 347
        },
        {
          "section": "14",
          "row": "3",
          "price": 356
        },
        {
          "section": "15",
          "row": "3",
          "price": 408
        }
      ],
      "parkingListings": [
        {
          "lot": "29",
          "price": 39
        },
        {
          "lot": "29",
          "price": 43
        },
        {
          "lot": "29",
          "price": 86
        }
      ],
      "parkingPrice": 39
    },
    "6": {
      "id": 6,
      "label": "Sun, Jun 7, 2026 · 1:30 PM · vs Pirates",
      "url": "https://www.stubhub.com/atlanta-braves-atlanta-tickets-6-7-2026/event/159262131/",
      "listings": [
        {
          "section": "13",
          "row": "11",
          "price": 176
        },
        {
          "section": "13",
          "row": "13",
          "price": 176
        },
        {
          "section": "13",
          "row": "9",
          "price": 179
        },
        {
          "section": "14",
          "row": "6",
          "price": 187
        },
        {
          "section": "13",
          "row": "5",
          "price": 188
        },
        {
          "section": "14",
          "row": "5",
          "price": 193
        },
        {
          "section": "13",
          "row": "1",
          "price": 214
        },
        {
          "section": "14",
          "row": "3",
          "price": 218
        },
        {
          "section": "14",
          "row": "2",
          "price": 227
        },
        {
          "section": "15",
          "row": "3",
          "price": 245
        }
      ],
      "parkingListings": [
        {
          "lot": "29",
          "price": 52
        },
        {
          "lot": "29",
          "price": 287
        }
      ],
      "parkingPrice": 52
    },
    "7": {
      "id": 7,
      "label": "Tue, Jun 16, 2026 · 7:15 PM · vs Giants",
      "url": "https://www.stubhub.com/atlanta-braves-atlanta-tickets-6-16-2026/event/159262132/",
      "listings": [
        {
          "section": "13",
          "row": "3",
          "price": 186
        },
        {
          "section": "14",
          "row": "6",
          "price": 195
        },
        {
          "section": "13",
          "row": "2",
          "price": 202
        },
        {
          "section": "14",
          "row": "2",
          "price": 232
        },
        {
          "section": "15",
          "row": "3",
          "price": 499
        },
        {
          "section": "14",
          "row": "3",
          "price": 499
        }
      ],
      "parkingListings": [
        {
          "lot": "29",
          "price": 66
        },
        {
          "lot": "29",
          "price": 472
        }
      ],
      "parkingPrice": 66
    },
    "8": {
      "id": 8,
      "label": "Wed, Jun 17, 2026 · 7:15 PM · vs Giants",
      "url": "https://www.stubhub.com/atlanta-braves-atlanta-tickets-6-17-2026/event/159262133/",
      "listings": [
        {
          "section": "13",
          "row": "13",
          "price": 182
        },
        {
          "section": "13",
          "row": "7",
          "price": 184
        },
        {
          "section": "13",
          "row": "6",
          "price": 186
        },
        {
          "section": "14",
          "row": "10",
          "price": 186
        },
        {
          "section": "13",
          "row": "5",
          "price": 193
        },
        {
          "section": "14",
          "row": "6",
          "price": 201
        },
        {
          "section": "15",
          "row": "4",
          "price": 215
        },
        {
          "section": "15",
          "row": "3",
          "price": 222
        },
        {
          "section": "14",
          "row": "3",
          "price": 222
        },
        {
          "section": "14",
          "row": "2",
          "price": 237
        },
        {
          "section": "15",
          "row": "2",
          "price": 247
        }
      ],
      "parkingListings": [
        {
          "lot": "29",
          "price": 61
        },
        {
          "lot": "29",
          "price": 472
        }
      ],
      "parkingPrice": 61
    },
    "9": {
      "id": 9,
      "label": "Thu, Jun 18, 2026 · 7:15 PM · vs Giants",
      "url": "https://www.stubhub.com/atlanta-braves-atlanta-tickets-6-18-2026/event/159262134/",
      "listings": [
        {
          "section": "13",
          "row": "8",
          "price": 182
        },
        {
          "section": "13",
          "row": "10",
          "price": 182
        },
        {
          "section": "13",
          "row": "13",
          "price": 182
        },
        {
          "section": "14",
          "row": "6",
          "price": 183
        },
        {
          "section": "13",
          "row": "5",
          "price": 186
        },
        {
          "section": "13",
          "row": "7",
          "price": 186
        },
        {
          "section": "13",
          "row": "2",
          "price": 198
        },
        {
          "section": "15",
          "row": "6",
          "price": 206
        },
        {
          "section": "15",
          "row": "3",
          "price": 215
        },
        {
          "section": "14",
          "row": "2",
          "price": 227
        },
        {
          "section": "14",
          "row": "3",
          "price": 451
        }
      ],
      "parkingListings": [
        {
          "lot": "29",
          "price": 158
        },
        {
          "lot": "29",
          "price": 301
        }
      ],
      "parkingPrice": 158
    },
    "10": {
      "id": 10,
      "label": "Fri, Jun 19, 2026 · 7:15 PM · vs Brewers",
      "url": "https://www.stubhub.com/atlanta-braves-atlanta-tickets-6-19-2026/event/159262135/",
      "listings": [
        {
          "section": "14",
          "row": "10",
          "price": 240
        },
        {
          "section": "13",
          "row": "5",
          "price": 253
        },
        {
          "section": "13",
          "row": "3",
          "price": 274
        },
        {
          "section": "13",
          "row": "2",
          "price": 293
        },
        {
          "section": "15",
          "row": "6",
          "price": 294
        },
        {
          "section": "14",
          "row": "5",
          "price": 294
        },
        {
          "section": "13",
          "row": "1",
          "price": 315
        },
        {
          "section": "14",
          "row": "2",
          "price": 332
        },
        {
          "section": "14",
          "row": "1",
          "price": 354
        },
        {
          "section": "15",
          "row": "4",
          "price": 404
        },
        {
          "section": "14",
          "row": "3",
          "price": 905
        }
      ],
      "parkingListings": [
        {
          "lot": "29",
          "price": 75
        },
        {
          "lot": "29",
          "price": 82
        }
      ],
      "parkingPrice": 75
    },
    "11": {
      "id": 11,
      "label": "Sat, Jun 20, 2026 · 7:15 PM · vs Brewers",
      "url": "https://www.stubhub.com/atlanta-braves-atlanta-tickets-6-20-2026/event/159262136/",
      "listings": [
        {
          "section": "13",
          "row": "4",
          "price": 267
        },
        {
          "section": "13",
          "row": "3",
          "price": 281
        },
        {
          "section": "14",
          "row": "6",
          "price": 294
        },
        {
          "section": "13",
          "row": "2",
          "price": 308
        },
        {
          "section": "14",
          "row": "4",
          "price": 309
        },
        {
          "section": "15",
          "row": "2",
          "price": 315
        },
        {
          "section": "14",
          "row": "2",
          "price": 350
        },
        {
          "section": "15",
          "row": "3",
          "price": 465
        },
        {
          "section": "15",
          "row": "4",
          "price": 548
        },
        {
          "section": "14",
          "row": "3",
          "price": 548
        }
      ],
      "parkingListings": [
        {
          "lot": "29",
          "price": 53
        }
      ],
      "parkingPrice": 53
    },
    "12": {
      "id": 12,
      "label": "Sun, Jun 21, 2026 · 1:30 PM · vs Brewers",
      "url": "https://www.stubhub.com/atlanta-braves-atlanta-tickets-6-21-2026/event/159262137/",
      "listings": [
        {
          "section": "13",
          "row": "3",
          "price": 240
        },
        {
          "section": "14",
          "row": "6",
          "price": 252
        },
        {
          "section": "13",
          "row": "2",
          "price": 261
        },
        {
          "section": "15",
          "row": "5",
          "price": 265
        },
        {
          "section": "13",
          "row": "1",
          "price": 282
        },
        {
          "section": "14",
          "row": "3",
          "price": 293
        },
        {
          "section": "14",
          "row": "2",
          "price": 299
        },
        {
          "section": "15",
          "row": "2",
          "price": 308
        },
        {
          "section": "14",
          "row": "1",
          "price": 319
        },
        {
          "section": "15",
          "row": "4",
          "price": 459
        }
      ],
      "parkingListings": [
        {
          "lot": "29",
          "price": 45
        },
        {
          "lot": "29",
          "price": 472
        }
      ],
      "parkingPrice": 45
    },
    "13": {
      "id": 13,
      "label": "Tue, Jun 30, 2026 · 7:15 PM · vs Cardinals",
      "url": "https://www.stubhub.com/atlanta-braves-atlanta-tickets-6-30-2026/event/159262138/",
      "listings": [
        {
          "section": "13",
          "row": "3",
          "price": 190
        },
        {
          "section": "14",
          "row": "10",
          "price": 197
        },
        {
          "section": "14",
          "row": "8",
          "price": 198
        },
        {
          "section": "14",
          "row": "6",
          "price": 200
        },
        {
          "section": "15",
          "row": "6",
          "price": 205
        },
        {
          "section": "14",
          "row": "5",
          "price": 206
        },
        {
          "section": "13",
          "row": "2",
          "price": 216
        },
        {
          "section": "15",
          "row": "5",
          "price": 231
        },
        {
          "section": "15",
          "row": "3",
          "price": 253
        },
        {
          "section": "15",
          "row": "2",
          "price": 258
        },
        {
          "section": "14",
          "row": "1",
          "price": 266
        },
        {
          "section": "14",
          "row": "3",
          "price": 482
        }
      ],
      "parkingListings": [
        {
          "lot": "29",
          "price": 61
        },
        {
          "lot": "29",
          "price": 145
        }
      ],
      "parkingPrice": 61
    },
    "14": {
      "id": 14,
      "label": "Wed, Jul 1, 2026 · 7:15 PM · vs Cardinals",
      "url": "https://www.stubhub.com/atlanta-braves-atlanta-tickets-7-1-2026/event/159262139/",
      "listings": [
        {
          "section": "13",
          "row": "6",
          "price": 184
        },
        {
          "section": "14",
          "row": "10",
          "price": 184
        },
        {
          "section": "13",
          "row": "7",
          "price": 184
        },
        {
          "section": "13",
          "row": "9",
          "price": 184
        },
        {
          "section": "13",
          "row": "10",
          "price": 184
        },
        {
          "section": "13",
          "row": "11",
          "price": 184
        },
        {
          "section": "13",
          "row": "12",
          "price": 184
        },
        {
          "section": "13",
          "row": "13",
          "price": 184
        },
        {
          "section": "13",
          "row": "3",
          "price": 186
        },
        {
          "section": "14",
          "row": "3",
          "price": 187
        },
        {
          "section": "14",
          "row": "5",
          "price": 187
        },
        {
          "section": "13",
          "row": "2",
          "price": 204
        },
        {
          "section": "14",
          "row": "3",
          "price": 217
        },
        {
          "section": "15",
          "row": "6",
          "price": 220
        },
        {
          "section": "13",
          "row": "1",
          "price": 220
        },
        {
          "section": "15",
          "row": "5",
          "price": 225
        },
        {
          "section": "15",
          "row": "3",
          "price": 232
        },
        {
          "section": "14",
          "row": "2",
          "price": 234
        },
        {
          "section": "15",
          "row": "2",
          "price": 243
        },
        {
          "section": "14",
          "row": "1",
          "price": 250
        },
        {
          "section": "15",
          "row": "4",
          "price": 469
        },
        {
          "section": "15",
          "row": "1",
          "price": 927
        }
      ],
      "parkingListings": [
        {
          "lot": "29",
          "price": 54
        },
        {
          "lot": "29",
          "price": 54
        }
      ],
      "parkingPrice": 54
    },
    "15": {
      "id": 15,
      "label": "Thu, Jul 2, 2026 · 7:15 PM · vs Cardinals",
      "url": "https://www.stubhub.com/atlanta-braves-atlanta-tickets-7-2-2026/event/159262140/",
      "listings": [
        {
          "section": "13",
          "row": "10",
          "price": 206
        },
        {
          "section": "13",
          "row": "8",
          "price": 232
        },
        {
          "section": "13",
          "row": "7",
          "price": 235
        },
        {
          "section": "14",
          "row": "10",
          "price": 242
        },
        {
          "section": "14",
          "row": "5",
          "price": 244
        },
        {
          "section": "14",
          "row": "7",
          "price": 244
        },
        {
          "section": "13",
          "row": "5",
          "price": 244
        },
        {
          "section": "13",
          "row": "3",
          "price": 276
        },
        {
          "section": "15",
          "row": "3",
          "price": 276
        },
        {
          "section": "14",
          "row": "3",
          "price": 276
        },
        {
          "section": "13",
          "row": "2",
          "price": 303
        },
        {
          "section": "14",
          "row": "2",
          "price": 345
        },
        {
          "section": "14",
          "row": "1",
          "price": 368
        },
        {
          "section": "15",
          "row": "4",
          "price": 476
        }
      ],
      "parkingListings": [
        {
          "lot": "29",
          "price": 45
        },
        {
          "lot": "29",
          "price": 63
        }
      ],
      "parkingPrice": 45
    },
    "16": {
      "id": 16,
      "label": "Fri, Jul 3, 2026 · 7:15 PM · vs Mets",
      "url": "https://www.stubhub.com/atlanta-braves-atlanta-tickets-7-3-2026/event/159262141/",
      "listings": [
        {
          "section": "13",
          "row": "10",
          "price": 233
        },
        {
          "section": "14",
          "row": "10",
          "price": 272
        },
        {
          "section": "13",
          "row": "7",
          "price": 303
        },
        {
          "section": "13",
          "row": "6",
          "price": 306
        },
        {
          "section": "13",
          "row": "3",
          "price": 309
        },
        {
          "section": "14",
          "row": "8",
          "price": 317
        },
        {
          "section": "14",
          "row": "6",
          "price": 323
        },
        {
          "section": "15",
          "row": "6",
          "price": 364
        },
        {
          "section": "15",
          "row": "5",
          "price": 372
        },
        {
          "section": "14",
          "row": "2",
          "price": 396
        },
        {
          "section": "15",
          "row": "2",
          "price": 411
        },
        {
          "section": "14",
          "row": "1",
          "price": 421
        },
        {
          "section": "15",
          "row": "3",
          "price": 561
        },
        {
          "section": "14",
          "row": "3",
          "price": 561
        },
        {
          "section": "15",
          "row": "4",
          "price": 670
        }
      ],
      "parkingListings": [
        {
          "lot": "29",
          "price": 53
        },
        {
          "lot": "29",
          "price": 56
        }
      ],
      "parkingPrice": 53
    },
    "17": {
      "id": 17,
      "label": "Sat, Jul 4, 2026 · 7:15 PM · vs Mets",
      "url": "https://www.stubhub.com/atlanta-braves-atlanta-tickets-7-4-2026/event/159262142/",
      "listings": [
        {
          "section": "13",
          "row": "10",
          "price": 345
        },
        {
          "section": "14",
          "row": "10",
          "price": 397
        },
        {
          "section": "13",
          "row": "6",
          "price": 399
        },
        {
          "section": "13",
          "row": "8",
          "price": 399
        },
        {
          "section": "14",
          "row": "7",
          "price": 414
        },
        {
          "section": "13",
          "row": "5",
          "price": 414
        },
        {
          "section": "13",
          "row": "4",
          "price": 428
        },
        {
          "section": "14",
          "row": "3",
          "price": 442
        },
        {
          "section": "15",
          "row": "2",
          "price": 474
        },
        {
          "section": "13",
          "row": "2",
          "price": 481
        },
        {
          "section": "14",
          "row": "2",
          "price": 540
        },
        {
          "section": "14",
          "row": "1",
          "price": 573
        },
        {
          "section": "15",
          "row": "3",
          "price": 639
        },
        {
          "section": "15",
          "row": "4",
          "price": 792
        }
      ],
      "parkingListings": [
        {
          "lot": "29",
          "price": 68
        }
      ],
      "parkingPrice": 68
    },
    "18": {
      "id": 18,
      "label": "Sun, Jul 5, 2026 · 12:30 PM · vs Mets",
      "url": "https://www.stubhub.com/atlanta-braves-atlanta-tickets-7-5-2026/event/159262143/",
      "listings": [
        {
          "section": "13",
          "row": "10",
          "price": 167
        },
        {
          "section": "14",
          "row": "10",
          "price": 197
        },
        {
          "section": "13",
          "row": "3",
          "price": 226
        },
        {
          "section": "14",
          "row": "8",
          "price": 226
        },
        {
          "section": "14",
          "row": "5",
          "price": 232
        },
        {
          "section": "14",
          "row": "4",
          "price": 240
        },
        {
          "section": "13",
          "row": "2",
          "price": 240
        },
        {
          "section": "13",
          "row": "1",
          "price": 260
        },
        {
          "section": "15",
          "row": "6",
          "price": 267
        },
        {
          "section": "14",
          "row": "3",
          "price": 272
        },
        {
          "section": "15",
          "row": "5",
          "price": 273
        },
        {
          "section": "15",
          "row": "2",
          "price": 274
        },
        {
          "section": "14",
          "row": "2",
          "price": 275
        },
        {
          "section": "14",
          "row": "1",
          "price": 294
        },
        {
          "section": "15",
          "row": "4",
          "price": 526
        }
      ],
      "parkingListings": [
        {
          "lot": "29",
          "price": 36
        }
      ],
      "parkingPrice": 36
    },
    "19": {
      "id": 19,
      "label": "Mon, Jul 6, 2026 · 7:15 PM · vs Mets",
      "url": "https://www.stubhub.com/atlanta-braves-atlanta-tickets-7-6-2026/event/159262144/",
      "listings": [
        {
          "section": "13",
          "row": "3",
          "price": 221
        },
        {
          "section": "14",
          "row": "6",
          "price": 233
        },
        {
          "section": "13",
          "row": "2",
          "price": 238
        },
        {
          "section": "13",
          "row": "1",
          "price": 257
        },
        {
          "section": "15",
          "row": "6",
          "price": 262
        },
        {
          "section": "14",
          "row": "2",
          "price": 272
        },
        {
          "section": "15",
          "row": "2",
          "price": 283
        },
        {
          "section": "14",
          "row": "1",
          "price": 291
        },
        {
          "section": "15",
          "row": "3",
          "price": 467
        },
        {
          "section": "14",
          "row": "3",
          "price": 467
        },
        {
          "section": "15",
          "row": "4",
          "price": 498
        }
      ],
      "parkingListings": [
        {
          "lot": "29",
          "price": 45
        },
        {
          "lot": "29",
          "price": 62
        }
      ],
      "parkingPrice": 45
    },
    "20": {
      "id": 20,
      "label": "Fri, Jul 17, 2026 · 7:15 PM · vs Rangers",
      "url": "https://www.stubhub.com/atlanta-braves-atlanta-tickets-7-17-2026/event/159262145/",
      "listings": [
        {
          "section": "13",
          "row": "10",
          "price": 203
        },
        {
          "section": "14",
          "row": "10",
          "price": 237
        },
        {
          "section": "13",
          "row": "5",
          "price": 250
        },
        {
          "section": "13",
          "row": "3",
          "price": 272
        },
        {
          "section": "14",
          "row": "6",
          "price": 284
        },
        {
          "section": "15",
          "row": "5",
          "price": 298
        },
        {
          "section": "13",
          "row": "2",
          "price": 298
        },
        {
          "section": "14",
          "row": "4",
          "price": 299
        },
        {
          "section": "14",
          "row": "2",
          "price": 338
        },
        {
          "section": "15",
          "row": "4",
          "price": 339
        },
        {
          "section": "15",
          "row": "2",
          "price": 351
        },
        {
          "section": "14",
          "row": "3",
          "price": 367
        },
        {
          "section": "15",
          "row": "3",
          "price": 561
        }
      ],
      "parkingListings": [
        {
          "lot": "29",
          "price": 54
        }
      ],
      "parkingPrice": 54
    },
    "21": {
      "id": 21,
      "label": "Sat, Jul 18, 2026 · 4:10 PM · vs Rangers",
      "url": "https://www.stubhub.com/atlanta-braves-atlanta-tickets-7-18-2026/event/159262146/",
      "listings": [
        {
          "section": "14",
          "row": "10",
          "price": 263
        },
        {
          "section": "13",
          "row": "5",
          "price": 277
        },
        {
          "section": "13",
          "row": "3",
          "price": 299
        },
        {
          "section": "14",
          "row": "6",
          "price": 313
        },
        {
          "section": "15",
          "row": "6",
          "price": 320
        },
        {
          "section": "13",
          "row": "2",
          "price": 325
        },
        {
          "section": "14",
          "row": "4",
          "price": 329
        },
        {
          "section": "14",
          "row": "2",
          "price": 369
        },
        {
          "section": "15",
          "row": "2",
          "price": 382
        },
        {
          "section": "15",
          "row": "3",
          "price": 431
        },
        {
          "section": "14",
          "row": "3",
          "price": 435
        },
        {
          "section": "15",
          "row": "4",
          "price": 512
        },
        {
          "section": "13",
          "row": "1",
          "price": 738
        }
      ],
      "parkingListings": [
        {
          "lot": "29",
          "price": 46
        },
        {
          "lot": "29",
          "price": 61
        }
      ],
      "parkingPrice": 46
    },
    "22": {
      "id": 22,
      "label": "Sun, Jul 19, 2026 · 1:30 PM · vs Rangers",
      "url": "https://www.stubhub.com/atlanta-braves-atlanta-tickets-7-19-2026/event/159262147/",
      "listings": [
        {
          "section": "14",
          "row": "7",
          "price": 181
        },
        {
          "section": "14",
          "row": "8",
          "price": 181
        },
        {
          "section": "14",
          "row": "10",
          "price": 181
        },
        {
          "section": "13",
          "row": "11",
          "price": 181
        },
        {
          "section": "13",
          "row": "12",
          "price": 181
        },
        {
          "section": "13",
          "row": "13",
          "price": 181
        },
        {
          "section": "13",
          "row": "6",
          "price": 183
        },
        {
          "section": "14",
          "row": "3",
          "price": 185
        },
        {
          "section": "13",
          "row": "5",
          "price": 185
        },
        {
          "section": "13",
          "row": "4",
          "price": 191
        },
        {
          "section": "13",
          "row": "3",
          "price": 201
        },
        {
          "section": "14",
          "row": "3",
          "price": 214
        },
        {
          "section": "13",
          "row": "2",
          "price": 219
        },
        {
          "section": "15",
          "row": "6",
          "price": 238
        },
        {
          "section": "13",
          "row": "1",
          "price": 238
        },
        {
          "section": "15",
          "row": "5",
          "price": 244
        },
        {
          "section": "14",
          "row": "2",
          "price": 252
        },
        {
          "section": "15",
          "row": "2",
          "price": 262
        },
        {
          "section": "14",
          "row": "1",
          "price": 269
        },
        {
          "section": "15",
          "row": "3",
          "price": 440
        },
        {
          "section": "15",
          "row": "4",
          "price": 453
        }
      ],
      "parkingListings": [
        {
          "lot": "29",
          "price": 46
        },
        {
          "lot": "29",
          "price": 76
        }
      ],
      "parkingPrice": 46
    },
    "23": {
      "id": 23,
      "label": "Mon, Jul 20, 2026 · 7:15 PM · vs Padres",
      "url": "https://www.stubhub.com/atlanta-braves-atlanta-tickets-7-20-2026/event/159262148/",
      "listings": [
        {
          "section": "13",
          "row": "3",
          "price": 199
        },
        {
          "section": "14",
          "row": "6",
          "price": 209
        },
        {
          "section": "14",
          "row": "3",
          "price": 212
        },
        {
          "section": "14",
          "row": "4",
          "price": 212
        },
        {
          "section": "13",
          "row": "2",
          "price": 214
        },
        {
          "section": "14",
          "row": "3",
          "price": 241
        },
        {
          "section": "14",
          "row": "2",
          "price": 245
        },
        {
          "section": "15",
          "row": "2",
          "price": 255
        },
        {
          "section": "14",
          "row": "1",
          "price": 262
        },
        {
          "section": "15",
          "row": "4",
          "price": 498
        }
      ],
      "parkingListings": [
        {
          "lot": "29",
          "price": 59
        }
      ],
      "parkingPrice": 59
    },
    "24": {
      "id": 24,
      "label": "Tue, Jul 21, 2026 · 7:15 PM · vs Padres",
      "url": "https://www.stubhub.com/atlanta-braves-atlanta-tickets-7-21-2026/event/159262149/",
      "listings": [
        {
          "section": "13",
          "row": "3",
          "price": 187
        },
        {
          "section": "14",
          "row": "6",
          "price": 197
        },
        {
          "section": "13",
          "row": "2",
          "price": 206
        },
        {
          "section": "15",
          "row": "6",
          "price": 223
        },
        {
          "section": "13",
          "row": "1",
          "price": 223
        },
        {
          "section": "14",
          "row": "2",
          "price": 236
        },
        {
          "section": "14",
          "row": "1",
          "price": 253
        },
        {
          "section": "15",
          "row": "4",
          "price": 329
        },
        {
          "section": "14",
          "row": "3",
          "price": 329
        }
      ],
      "parkingListings": [
        {
          "lot": "29",
          "price": 36
        }
      ],
      "parkingPrice": 36
    }
  }
}