{
  "lastUpdated": "2026-07-13T07:59:35.614Z",
  "sections": [
    "13",
    "14",
    "15"
  ],
  "games": {
    "1": {
      "id": 1,
      "label": "Fri, Jul 17, 2026 · 7:15 PM · vs Rangers",
      "url": "https://www.stubhub.com/atlanta-braves-atlanta-tickets-7-17-2026/event/159262145/",
      "listings": [
        {
          "section": "13",
          "row": "5",
          "price": 220
        },
        {
          "section": "13",
          "row": "4",
          "price": 226
        },
        {
          "section": "14",
          "row": "3",
          "price": 241
        },
        {
          "section": "15",
          "row": "5",
          "price": 262
        },
        {
          "section": "14",
          "row": "2",
          "price": 293
        }
      ],
      "parkingListings": [
        {
          "lot": "29",
          "price": 59
        }
      ],
      "parkingPrice": 59
    },
    "2": {
      "id": 2,
      "label": "Sat, Jul 18, 2026 · 4:10 PM · vs Rangers",
      "url": "https://www.stubhub.com/atlanta-braves-atlanta-tickets-7-18-2026/event/159262146/",
      "listings": [
        {
          "section": "13",
          "row": "5",
          "price": 173
        },
        {
          "section": "13",
          "row": "3",
          "price": 189
        },
        {
          "section": "14",
          "row": "6",
          "price": 198
        },
        {
          "section": "13",
          "row": "2",
          "price": 201
        },
        {
          "section": "15",
          "row": "6",
          "price": 204
        },
        {
          "section": "14",
          "row": "4",
          "price": 210
        },
        {
          "section": "14",
          "row": "2",
          "price": 232
        },
        {
          "section": "15",
          "row": "2",
          "price": 241
        }
      ],
      "parkingListings": [
        {
          "lot": "29",
          "price": 54
        },
        {
          "lot": "29",
          "price": 58
        }
      ],
      "parkingPrice": 54
    },
    "3": {
      "id": 3,
      "label": "Sun, Jul 19, 2026 · 1:30 PM · vs Rangers",
      "url": "https://www.stubhub.com/atlanta-braves-atlanta-tickets-7-19-2026/event/159262147/",
      "listings": [
        {
          "section": "13",
          "row": "4",
          "price": 90
        },
        {
          "section": "13",
          "row": "3",
          "price": 95
        },
        {
          "section": "14",
          "row": "6",
          "price": 101
        },
        {
          "section": "13",
          "row": "2",
          "price": 106
        },
        {
          "section": "14",
          "row": "2",
          "price": 122
        },
        {
          "section": "15",
          "row": "2",
          "price": 128
        }
      ],
      "parkingListings": [
        {
          "lot": "29",
          "price": 49
        },
        {
          "lot": "29",
          "price": 76
        }
      ],
      "parkingPrice": 49
    },
    "4": {
      "id": 4,
      "label": "Mon, Jul 20, 2026 · 7:15 PM · vs Padres",
      "url": "https://www.stubhub.com/atlanta-braves-atlanta-tickets-7-20-2026/event/159262148/",
      "listings": [
        {
          "section": "13",
          "row": "3",
          "price": 105
        },
        {
          "section": "14",
          "row": "6",
          "price": 111
        },
        {
          "section": "13",
          "row": "2",
          "price": 116
        },
        {
          "section": "14",
          "row": "3",
          "price": 365
        },
        {
          "section": "15",
          "row": "4",
          "price": 438
        }
      ],
      "parkingListings": [
        {
          "lot": "29",
          "price": 57
        }
      ],
      "parkingPrice": 57
    },
    "5": {
      "id": 5,
      "label": "Tue, Jul 21, 2026 · 7:15 PM · vs Padres",
      "url": "https://www.stubhub.com/atlanta-braves-atlanta-tickets-7-21-2026/event/159262149/",
      "listings": [
        {
          "section": "13",
          "row": "12",
          "price": 75
        },
        {
          "section": "13",
          "row": "7",
          "price": 95
        },
        {
          "section": "14",
          "row": "10",
          "price": 95
        },
        {
          "section": "14",
          "row": "6",
          "price": 116
        },
        {
          "section": "14",
          "row": "5",
          "price": 120
        },
        {
          "section": "13",
          "row": "2",
          "price": 121
        },
        {
          "section": "14",
          "row": "2",
          "price": 141
        },
        {
          "section": "15",
          "row": "3",
          "price": 142
        }
      ],
      "parkingListings": [
        {
          "lot": "29",
          "price": 48
        }
      ],
      "parkingPrice": 48
    },
    "6": {
      "id": 6,
      "label": "Wed, Jul 22, 2026 · 7:15 PM · vs Padres",
      "url": "https://www.stubhub.com/atlanta-braves-atlanta-tickets-7-22-2026/event/159262150/",
      "listings": [
        {
          "section": "13",
          "row": "13",
          "price": 86
        },
        {
          "section": "13",
          "row": "12",
          "price": 87
        },
        {
          "section": "13",
          "row": "7",
          "price": 111
        },
        {
          "section": "13",
          "row": "4",
          "price": 122
        },
        {
          "section": "14",
          "row": "6",
          "price": 136
        },
        {
          "section": "14",
          "row": "5",
          "price": 140
        },
        {
          "section": "13",
          "row": "2",
          "price": 141
        },
        {
          "section": "14",
          "row": "2",
          "price": 163
        },
        {
          "section": "14",
          "row": "1",
          "price": 176
        },
        {
          "section": "15",
          "row": "3",
          "price": 401
        },
        {
          "section": "15",
          "row": "4",
          "price": 401
        }
      ],
      "parkingListings": [
        {
          "lot": "29",
          "price": 48
        }
      ],
      "parkingPrice": 48
    },
    "7": {
      "id": 7,
      "label": "Thu, Jul 23, 2026 · 12:15 PM · vs Padres",
      "url": "https://www.stubhub.com/atlanta-braves-atlanta-tickets-7-23-2026/event/159262151/",
      "listings": [
        {
          "section": "13",
          "row": "3",
          "price": 112
        },
        {
          "section": "14",
          "row": "6",
          "price": 120
        },
        {
          "section": "14",
          "row": "5",
          "price": 122
        },
        {
          "section": "13",
          "row": "1",
          "price": 141
        },
        {
          "section": "14",
          "row": "1",
          "price": 162
        },
        {
          "section": "15",
          "row": "3",
          "price": 234
        }
      ],
      "parkingListings": [
        {
          "lot": "29",
          "price": 93
        },
        {
          "lot": "29",
          "price": 94
        }
      ],
      "parkingPrice": 93
    },
    "8": {
      "id": 8,
      "label": "Thu, Jul 30, 2026 · 7:15 PM · vs Nationals",
      "url": "https://www.stubhub.com/atlanta-braves-atlanta-tickets-7-30-2026/event/159262152/",
      "listings": [
        {
          "section": "13",
          "row": "4",
          "price": 147
        },
        {
          "section": "14",
          "row": "6",
          "price": 163
        },
        {
          "section": "15",
          "row": "5",
          "price": 172
        },
        {
          "section": "14",
          "row": "2",
          "price": 197
        },
        {
          "section": "15",
          "row": "2",
          "price": 206
        }
      ],
      "parkingListings": [
        {
          "lot": "29",
          "price": 49
        },
        {
          "lot": "29",
          "price": 52
        }
      ],
      "parkingPrice": 49
    },
    "9": {
      "id": 9,
      "label": "Fri, Jul 31, 2026 · 7:15 PM · vs Nationals",
      "url": "https://www.stubhub.com/atlanta-braves-atlanta-tickets-7-31-2026/event/159262153/",
      "listings": [
        {
          "section": "13",
          "row": "3",
          "price": 187
        },
        {
          "section": "14",
          "row": "6",
          "price": 201
        },
        {
          "section": "13",
          "row": "2",
          "price": 205
        },
        {
          "section": "14",
          "row": "5",
          "price": 206
        },
        {
          "section": "13",
          "row": "1",
          "price": 221
        },
        {
          "section": "14",
          "row": "2",
          "price": 234
        },
        {
          "section": "15",
          "row": "3",
          "price": 375
        }
      ],
      "parkingListings": [
        {
          "lot": "29",
          "price": 59
        }
      ],
      "parkingPrice": 59
    },
    "10": {
      "id": 10,
      "label": "Sat, Aug 1, 2026 · 7:15 PM · vs Nationals",
      "url": "https://www.stubhub.com/atlanta-braves-atlanta-tickets-8-1-2026/event/159262154/",
      "listings": [
        {
          "section": "13",
          "row": "5",
          "price": 167
        },
        {
          "section": "13",
          "row": "4",
          "price": 172
        },
        {
          "section": "14",
          "row": "6",
          "price": 190
        },
        {
          "section": "14",
          "row": "4",
          "price": 201
        },
        {
          "section": "13",
          "row": "1",
          "price": 212
        },
        {
          "section": "14",
          "row": "2",
          "price": 226
        },
        {
          "section": "15",
          "row": "2",
          "price": 234
        }
      ],
      "parkingListings": [
        {
          "lot": "29",
          "price": 113
        }
      ],
      "parkingPrice": 113
    },
    "11": {
      "id": 11,
      "label": "Sun, Aug 2, 2026 · 1:30 PM · vs Nationals",
      "url": "https://www.stubhub.com/atlanta-braves-atlanta-tickets-8-2-2026/event/159262155/",
      "listings": [
        {
          "section": "13",
          "row": "12",
          "price": 98
        },
        {
          "section": "13",
          "row": "8",
          "price": 108
        },
        {
          "section": "14",
          "row": "6",
          "price": 139
        },
        {
          "section": "14",
          "row": "5",
          "price": 142
        },
        {
          "section": "13",
          "row": "2",
          "price": 145
        },
        {
          "section": "13",
          "row": "1",
          "price": 157
        },
        {
          "section": "15",
          "row": "5",
          "price": 160
        },
        {
          "section": "14",
          "row": "2",
          "price": 168
        },
        {
          "section": "15",
          "row": "3",
          "price": 387
        },
        {
          "section": "15",
          "row": "4",
          "price": 387
        }
      ],
      "parkingListings": [
        {
          "lot": "29",
          "price": 36
        }
      ],
      "parkingPrice": 36
    },
    "12": {
      "id": 12,
      "label": "Tue, Aug 4, 2026 · 7:15 PM · vs Marlins",
      "url": "https://www.stubhub.com/atlanta-braves-atlanta-tickets-8-4-2026/event/159262156/",
      "listings": [
        {
          "section": "13",
          "row": "3",
          "price": 104
        },
        {
          "section": "13",
          "row": "2",
          "price": 111
        },
        {
          "section": "15",
          "row": "6",
          "price": 113
        },
        {
          "section": "13",
          "row": "1",
          "price": 121
        },
        {
          "section": "14",
          "row": "2",
          "price": 129
        },
        {
          "section": "15",
          "row": "2",
          "price": 134
        },
        {
          "section": "14",
          "row": "1",
          "price": 139
        }
      ],
      "parkingListings": [
        {
          "lot": "29",
          "price": 40
        }
      ],
      "parkingPrice": 40
    },
    "13": {
      "id": 13,
      "label": "Wed, Aug 5, 2026 · 7:15 PM · vs Marlins",
      "url": "https://www.stubhub.com/atlanta-braves-atlanta-tickets-8-5-2026/event/159262157/",
      "listings": [
        {
          "section": "13",
          "row": "13",
          "price": 77
        },
        {
          "section": "14",
          "row": "11",
          "price": 89
        },
        {
          "section": "13",
          "row": "6",
          "price": 99
        },
        {
          "section": "15",
          "row": "7",
          "price": 108
        },
        {
          "section": "13",
          "row": "2",
          "price": 117
        },
        {
          "section": "14",
          "row": "2",
          "price": 136
        },
        {
          "section": "15",
          "row": "2",
          "price": 142
        },
        {
          "section": "14",
          "row": "1",
          "price": 147
        }
      ],
      "parkingListings": [
        {
          "lot": "29",
          "price": 49
        }
      ],
      "parkingPrice": 49
    },
    "14": {
      "id": 14,
      "label": "Thu, Aug 6, 2026 · 7:15 PM · vs Marlins",
      "url": "https://www.stubhub.com/atlanta-braves-atlanta-tickets-8-6-2026/event/159262158/",
      "listings": [
        {
          "section": "13",
          "row": "9",
          "price": 157
        },
        {
          "section": "13",
          "row": "5",
          "price": 203
        },
        {
          "section": "14",
          "row": "8",
          "price": 210
        },
        {
          "section": "13",
          "row": "2",
          "price": 254
        },
        {
          "section": "14",
          "row": "3",
          "price": 263
        },
        {
          "section": "15",
          "row": "6",
          "price": 279
        },
        {
          "section": "14",
          "row": "2",
          "price": 312
        },
        {
          "section": "15",
          "row": "2",
          "price": 333
        },
        {
          "section": "14",
          "row": "1",
          "price": 348
        },
        {
          "section": "13",
          "row": "1",
          "price": 618
        }
      ],
      "parkingListings": [
        {
          "lot": "29",
          "price": 158
        }
      ],
      "parkingPrice": 158
    },
    "15": {
      "id": 15,
      "label": "Mon, Aug 10, 2026 · 7:15 PM · vs Mets",
      "url": "https://www.stubhub.com/atlanta-braves-atlanta-tickets-8-10-2026/event/159262159/",
      "listings": [
        {
          "section": "13",
          "row": "3",
          "price": 137
        },
        {
          "section": "14",
          "row": "6",
          "price": 144
        },
        {
          "section": "13",
          "row": "2",
          "price": 151
        },
        {
          "section": "15",
          "row": "5",
          "price": 152
        },
        {
          "section": "13",
          "row": "1",
          "price": 163
        },
        {
          "section": "14",
          "row": "2",
          "price": 175
        },
        {
          "section": "15",
          "row": "3",
          "price": 253
        }
      ],
      "parkingListings": [
        {
          "lot": "29",
          "price": 45
        }
      ],
      "parkingPrice": 45
    },
    "16": {
      "id": 16,
      "label": "Tue, Aug 11, 2026 · 7:15 PM · vs Mets",
      "url": "https://www.stubhub.com/atlanta-braves-atlanta-tickets-8-11-2026/event/159262160/",
      "listings": [
        {
          "section": "13",
          "row": "3",
          "price": 132
        },
        {
          "section": "14",
          "row": "6",
          "price": 139
        },
        {
          "section": "13",
          "row": "2",
          "price": 141
        },
        {
          "section": "15",
          "row": "6",
          "price": 143
        },
        {
          "section": "13",
          "row": "1",
          "price": 153
        },
        {
          "section": "14",
          "row": "2",
          "price": 163
        },
        {
          "section": "15",
          "row": "2",
          "price": 171
        },
        {
          "section": "14",
          "row": "1",
          "price": 176
        }
      ],
      "parkingListings": [
        {
          "lot": "29",
          "price": 45
        }
      ],
      "parkingPrice": 45
    },
    "17": {
      "id": 17,
      "label": "Wed, Aug 12, 2026 · 7:15 PM · vs Mets",
      "url": "https://www.stubhub.com/atlanta-braves-atlanta-tickets-8-12-2026/event/159262161/",
      "listings": [
        {
          "section": "13",
          "row": "3",
          "price": 134
        },
        {
          "section": "14",
          "row": "6",
          "price": 142
        },
        {
          "section": "15",
          "row": "6",
          "price": 146
        },
        {
          "section": "13",
          "row": "2",
          "price": 148
        },
        {
          "section": "15",
          "row": "5",
          "price": 149
        },
        {
          "section": "14",
          "row": "2",
          "price": 172
        },
        {
          "section": "15",
          "row": "2",
          "price": 180
        },
        {
          "section": "14",
          "row": "1",
          "price": 185
        }
      ],
      "parkingListings": [
        {
          "lot": "29",
          "price": 35
        },
        {
          "lot": "29",
          "price": 45
        }
      ],
      "parkingPrice": 35
    },
    "18": {
      "id": 18,
      "label": "Fri, Aug 14, 2026 · 7:15 PM · vs Diamondbacks",
      "url": "https://www.stubhub.com/atlanta-braves-atlanta-tickets-8-14-2026/event/159262162/",
      "listings": [
        {
          "section": "14",
          "row": "9",
          "price": 135
        },
        {
          "section": "14",
          "row": "6",
          "price": 156
        },
        {
          "section": "13",
          "row": "2",
          "price": 160
        },
        {
          "section": "13",
          "row": "1",
          "price": 173
        },
        {
          "section": "14",
          "row": "2",
          "price": 184
        },
        {
          "section": "14",
          "row": "1",
          "price": 198
        },
        {
          "section": "15",
          "row": "3",
          "price": 410
        }
      ],
      "parkingListings": [
        {
          "lot": "29",
          "price": 44
        },
        {
          "lot": "29",
          "price": 44
        }
      ],
      "parkingPrice": 44
    },
    "19": {
      "id": 19,
      "label": "Sat, Aug 15, 2026 · 7:15 PM · vs Diamondbacks",
      "url": "https://www.stubhub.com/atlanta-braves-atlanta-tickets-8-15-2026/event/159262163/",
      "listings": [
        {
          "section": "14",
          "row": "10",
          "price": 140
        },
        {
          "section": "13",
          "row": "4",
          "price": 153
        },
        {
          "section": "14",
          "row": "6",
          "price": 171
        },
        {
          "section": "15",
          "row": "6",
          "price": 176
        },
        {
          "section": "13",
          "row": "1",
          "price": 190
        },
        {
          "section": "14",
          "row": "2",
          "price": 203
        },
        {
          "section": "15",
          "row": "2",
          "price": 211
        },
        {
          "section": "14",
          "row": "1",
          "price": 218
        }
      ],
      "parkingListings": [
        {
          "lot": "29",
          "price": 54
        }
      ],
      "parkingPrice": 54
    },
    "20": {
      "id": 20,
      "label": "Sun, Aug 16, 2026 · 1:30 PM · vs Diamondbacks",
      "url": "https://www.stubhub.com/atlanta-braves-atlanta-tickets-8-16-2026/event/159262164/",
      "listings": [
        {
          "section": "13",
          "row": "3",
          "price": 119
        },
        {
          "section": "14",
          "row": "6",
          "price": 126
        },
        {
          "section": "13",
          "row": "2",
          "price": 136
        },
        {
          "section": "15",
          "row": "6",
          "price": 142
        },
        {
          "section": "15",
          "row": "5",
          "price": 146
        },
        {
          "section": "13",
          "row": "1",
          "price": 148
        },
        {
          "section": "14",
          "row": "2",
          "price": 158
        },
        {
          "section": "15",
          "row": "2",
          "price": 166
        }
      ],
      "parkingListings": [
        {
          "lot": "29",
          "price": 44
        }
      ],
      "parkingPrice": 44
    },
    "21": {
      "id": 21,
      "label": "Tue, Aug 25, 2026 · 7:15 PM · vs Dodgers",
      "url": "https://www.stubhub.com/atlanta-braves-atlanta-tickets-8-25-2026/event/159262165/",
      "listings": [
        {
          "section": "14",
          "row": "12",
          "price": 198
        },
        {
          "section": "14",
          "row": "10",
          "price": 206
        },
        {
          "section": "13",
          "row": "5",
          "price": 217
        },
        {
          "section": "13",
          "row": "3",
          "price": 236
        },
        {
          "section": "14",
          "row": "6",
          "price": 247
        },
        {
          "section": "14",
          "row": "5",
          "price": 254
        },
        {
          "section": "13",
          "row": "2",
          "price": 262
        },
        {
          "section": "15",
          "row": "6",
          "price": 279
        },
        {
          "section": "14",
          "row": "2",
          "price": 299
        },
        {
          "section": "15",
          "row": "2",
          "price": 311
        }
      ],
      "parkingListings": [
        {
          "lot": "29",
          "price": 64
        }
      ],
      "parkingPrice": 64
    },
    "22": {
      "id": 22,
      "label": "Wed, Aug 26, 2026 · 7:15 PM · vs Dodgers",
      "url": "https://www.stubhub.com/atlanta-braves-atlanta-tickets-8-26-2026/event/159262166/",
      "listings": [
        {
          "section": "13",
          "row": "13",
          "price": 163
        },
        {
          "section": "13",
          "row": "10",
          "price": 173
        },
        {
          "section": "13",
          "row": "3",
          "price": 234
        },
        {
          "section": "14",
          "row": "6",
          "price": 245
        },
        {
          "section": "15",
          "row": "6",
          "price": 251
        },
        {
          "section": "13",
          "row": "2",
          "price": 256
        },
        {
          "section": "14",
          "row": "4",
          "price": 258
        },
        {
          "section": "14",
          "row": "2",
          "price": 293
        },
        {
          "section": "14",
          "row": "1",
          "price": 313
        },
        {
          "section": "15",
          "row": "4",
          "price": 636
        }
      ],
      "parkingListings": [
        {
          "lot": "29",
          "price": 49
        }
      ],
      "parkingPrice": 49
    },
    "23": {
      "id": 23,
      "label": "Thu, Aug 27, 2026 · 7:15 PM · vs Dodgers",
      "url": "https://www.stubhub.com/atlanta-braves-atlanta-tickets-8-27-2026/event/159262167/",
      "listings": [
        {
          "section": "13",
          "row": "12",
          "price": 352
        },
        {
          "section": "13",
          "row": "5",
          "price": 354
        },
        {
          "section": "13",
          "row": "3",
          "price": 381
        },
        {
          "section": "14",
          "row": "6",
          "price": 399
        },
        {
          "section": "14",
          "row": "5",
          "price": 409
        },
        {
          "section": "15",
          "row": "5",
          "price": 418
        },
        {
          "section": "14",
          "row": "4",
          "price": 419
        },
        {
          "section": "13",
          "row": "2",
          "price": 428
        },
        {
          "section": "14",
          "row": "3",
          "price": 549
        }
      ],
      "parkingListings": [
        {
          "lot": "29",
          "price": 63
        }
      ],
      "parkingPrice": 63
    },
    "24": {
      "id": 24,
      "label": "Fri, Aug 28, 2026 · 7:15 PM · vs Rockies",
      "url": "https://www.stubhub.com/atlanta-braves-atlanta-tickets-8-28-2026/event/159262168/",
      "listings": [
        {
          "section": "14",
          "row": "6",
          "price": 156
        },
        {
          "section": "13",
          "row": "2",
          "price": 156
        },
        {
          "section": "15",
          "row": "6",
          "price": 161
        },
        {
          "section": "15",
          "row": "5",
          "price": 165
        },
        {
          "section": "13",
          "row": "1",
          "price": 169
        },
        {
          "section": "14",
          "row": "2",
          "price": 181
        },
        {
          "section": "15",
          "row": "2",
          "price": 188
        },
        {
          "section": "14",
          "row": "1",
          "price": 193
        },
        {
          "section": "15",
          "row": "1",
          "price": 826
        }
      ],
      "parkingListings": [
        {
          "lot": "29",
          "price": 50
        }
      ],
      "parkingPrice": 50
    },
    "25": {
      "id": 25,
      "label": "Sat, Aug 29, 2026 · 4:10 PM · vs Rockies",
      "url": "https://www.stubhub.com/atlanta-braves-atlanta-tickets-8-29-2026/event/159262169/",
      "listings": [
        {
          "section": "13",
          "row": "13",
          "price": 130
        },
        {
          "section": "13",
          "row": "3",
          "price": 188
        },
        {
          "section": "14",
          "row": "6",
          "price": 198
        },
        {
          "section": "13",
          "row": "2",
          "price": 207
        },
        {
          "section": "15",
          "row": "5",
          "price": 209
        },
        {
          "section": "14",
          "row": "2",
          "price": 237
        },
        {
          "section": "14",
          "row": "1",
          "price": 253
        },
        {
          "section": "15",
          "row": "3",
          "price": 410
        }
      ],
      "parkingListings": [
        {
          "lot": "29",
          "price": 45
        }
      ],
      "parkingPrice": 45
    },
    "26": {
      "id": 26,
      "label": "Sun, Aug 30, 2026 · 1:30 PM · vs Rockies",
      "url": "https://www.stubhub.com/atlanta-braves-atlanta-tickets-8-30-2026/event/159262170/",
      "listings": [
        {
          "section": "13",
          "row": "3",
          "price": 127
        },
        {
          "section": "14",
          "row": "6",
          "price": 135
        },
        {
          "section": "13",
          "row": "2",
          "price": 137
        },
        {
          "section": "13",
          "row": "1",
          "price": 150
        },
        {
          "section": "15",
          "row": "6",
          "price": 151
        },
        {
          "section": "14",
          "row": "2",
          "price": 160
        },
        {
          "section": "15",
          "row": "2",
          "price": 167
        },
        {
          "section": "14",
          "row": "1",
          "price": 172
        }
      ],
      "parkingListings": [
        {
          "lot": "29",
          "price": 42
        }
      ],
      "parkingPrice": 42
    },
    "27": {
      "id": 27,
      "label": "Mon, Aug 31, 2026 · 6:05 PM · vs Giants",
      "url": "https://www.stubhub.com/atlanta-braves-atlanta-tickets-8-31-2026/event/159262134/",
      "listings": [
        {
          "section": "13",
          "row": "10",
          "price": 113
        },
        {
          "section": "14",
          "row": "12",
          "price": 129
        },
        {
          "section": "14",
          "row": "3",
          "price": 169
        },
        {
          "section": "13",
          "row": "2",
          "price": 172
        },
        {
          "section": "15",
          "row": "4",
          "price": 187
        },
        {
          "section": "14",
          "row": "2",
          "price": 187
        },
        {
          "section": "15",
          "row": "3",
          "price": 195
        }
      ],
      "parkingListings": [
        {
          "lot": "29",
          "price": 40
        },
        {
          "lot": "29",
          "price": 43
        }
      ],
      "parkingPrice": 40
    },
    "28": {
      "id": 28,
      "label": "Tue, Sep 8, 2026 · 7:15 PM · vs Rays",
      "url": "https://www.stubhub.com/atlanta-braves-atlanta-tickets-9-8-2026/event/159262171/",
      "listings": [
        {
          "section": "13",
          "row": "3",
          "price": 119
        },
        {
          "section": "13",
          "row": "2",
          "price": 128
        },
        {
          "section": "15",
          "row": "3",
          "price": 139
        },
        {
          "section": "13",
          "row": "1",
          "price": 141
        },
        {
          "section": "14",
          "row": "3",
          "price": 148
        },
        {
          "section": "14",
          "row": "2",
          "price": 149
        },
        {
          "section": "15",
          "row": "2",
          "price": 157
        },
        {
          "section": "14",
          "row": "1",
          "price": 161
        }
      ],
      "parkingListings": [
        {
          "lot": "29",
          "price": 56
        },
        {
          "lot": "29",
          "price": 57
        }
      ],
      "parkingPrice": 56
    },
    "29": {
      "id": 29,
      "label": "Wed, Sep 9, 2026 · 7:15 PM · vs Rays",
      "url": "https://www.stubhub.com/atlanta-braves-atlanta-tickets-9-9-2026/event/159262172/",
      "listings": [
        {
          "section": "13",
          "row": "3",
          "price": 144
        },
        {
          "section": "13",
          "row": "2",
          "price": 158
        },
        {
          "section": "14",
          "row": "3",
          "price": 167
        },
        {
          "section": "15",
          "row": "6",
          "price": 171
        },
        {
          "section": "14",
          "row": "2",
          "price": 183
        },
        {
          "section": "15",
          "row": "3",
          "price": 185
        },
        {
          "section": "15",
          "row": "2",
          "price": 192
        },
        {
          "section": "14",
          "row": "1",
          "price": 197
        }
      ],
      "parkingListings": [
        {
          "lot": "29",
          "price": 44
        }
      ],
      "parkingPrice": 44
    },
    "30": {
      "id": 30,
      "label": "Thu, Sep 10, 2026 · 12:15 PM · vs Rays",
      "url": "https://www.stubhub.com/atlanta-braves-atlanta-tickets-9-10-2026/event/159262173/",
      "listings": [
        {
          "section": "13",
          "row": "3",
          "price": 106
        },
        {
          "section": "13",
          "row": "2",
          "price": 117
        },
        {
          "section": "15",
          "row": "6",
          "price": 126
        },
        {
          "section": "13",
          "row": "1",
          "price": 127
        },
        {
          "section": "15",
          "row": "5",
          "price": 129
        },
        {
          "section": "14",
          "row": "2",
          "price": 136
        },
        {
          "section": "15",
          "row": "2",
          "price": 142
        },
        {
          "section": "14",
          "row": "1",
          "price": 147
        }
      ],
      "parkingListings": [
        {
          "lot": "29",
          "price": 68
        }
      ],
      "parkingPrice": 68
    },
    "31": {
      "id": 31,
      "label": "Fri, Sep 11, 2026 · 7:15 PM · vs Phillies",
      "url": "https://www.stubhub.com/atlanta-braves-atlanta-tickets-9-11-2026/event/159262174/",
      "listings": [
        {
          "section": "13",
          "row": "13",
          "price": 136
        },
        {
          "section": "13",
          "row": "11",
          "price": 157
        },
        {
          "section": "13",
          "row": "8",
          "price": 166
        },
        {
          "section": "14",
          "row": "6",
          "price": 208
        },
        {
          "section": "15",
          "row": "6",
          "price": 213
        },
        {
          "section": "13",
          "row": "1",
          "price": 228
        },
        {
          "section": "15",
          "row": "5",
          "price": 240
        },
        {
          "section": "14",
          "row": "2",
          "price": 242
        },
        {
          "section": "15",
          "row": "2",
          "price": 252
        },
        {
          "section": "14",
          "row": "1",
          "price": 258
        }
      ],
      "parkingListings": [
        {
          "lot": "29",
          "price": 44
        }
      ],
      "parkingPrice": 44
    },
    "32": {
      "id": 32,
      "label": "Sat, Sep 12, 2026 · 7:15 PM · vs Phillies",
      "url": "https://www.stubhub.com/atlanta-braves-atlanta-tickets-9-12-2026/event/159262175/",
      "listings": [
        {
          "section": "13",
          "row": "13",
          "price": 141
        },
        {
          "section": "13",
          "row": "12",
          "price": 158
        },
        {
          "section": "14",
          "row": "10",
          "price": 178
        },
        {
          "section": "14",
          "row": "6",
          "price": 215
        },
        {
          "section": "14",
          "row": "4",
          "price": 226
        },
        {
          "section": "13",
          "row": "2",
          "price": 226
        },
        {
          "section": "14",
          "row": "2",
          "price": 260
        },
        {
          "section": "15",
          "row": "3",
          "price": 346
        }
      ],
      "parkingListings": [
        {
          "lot": "29",
          "price": 45
        }
      ],
      "parkingPrice": 45
    },
    "33": {
      "id": 33,
      "label": "Sun, Sep 13, 2026 · 1:30 PM · vs Phillies",
      "url": "https://www.stubhub.com/atlanta-braves-atlanta-tickets-9-13-2026/event/159262176/",
      "listings": [
        {
          "section": "14",
          "row": "6",
          "price": 171
        },
        {
          "section": "14",
          "row": "5",
          "price": 176
        },
        {
          "section": "13",
          "row": "2",
          "price": 182
        },
        {
          "section": "15",
          "row": "6",
          "price": 192
        },
        {
          "section": "13",
          "row": "1",
          "price": 197
        },
        {
          "section": "15",
          "row": "5",
          "price": 198
        },
        {
          "section": "14",
          "row": "2",
          "price": 209
        },
        {
          "section": "15",
          "row": "2",
          "price": 218
        },
        {
          "section": "14",
          "row": "1",
          "price": 224
        }
      ],
      "parkingListings": [
        {
          "lot": "29",
          "price": 49
        }
      ],
      "parkingPrice": 49
    },
    "34": {
      "id": 34,
      "label": "Tue, Sep 22, 2026 · 7:15 PM · vs Reds",
      "url": "https://www.stubhub.com/atlanta-braves-atlanta-tickets-9-22-2026/event/159262177/",
      "listings": [
        {
          "section": "14",
          "row": "6",
          "price": 136
        },
        {
          "section": "13",
          "row": "2",
          "price": 141
        },
        {
          "section": "15",
          "row": "5",
          "price": 143
        },
        {
          "section": "13",
          "row": "1",
          "price": 152
        },
        {
          "section": "14",
          "row": "2",
          "price": 163
        },
        {
          "section": "15",
          "row": "2",
          "price": 170
        }
      ],
      "parkingListings": [
        {
          "lot": "29",
          "price": 50
        },
        {
          "lot": "29",
          "price": 57
        }
      ],
      "parkingPrice": 50
    },
    "35": {
      "id": 35,
      "label": "Wed, Sep 23, 2026 · 7:15 PM · vs Reds",
      "url": "https://www.stubhub.com/atlanta-braves-atlanta-tickets-9-23-2026/event/159262178/",
      "listings": [
        {
          "section": "14",
          "row": "6",
          "price": 114
        },
        {
          "section": "13",
          "row": "2",
          "price": 116
        },
        {
          "section": "13",
          "row": "1",
          "price": 128
        },
        {
          "section": "15",
          "row": "5",
          "price": 132
        },
        {
          "section": "14",
          "row": "2",
          "price": 137
        },
        {
          "section": "15",
          "row": "2",
          "price": 143
        },
        {
          "section": "14",
          "row": "1",
          "price": 147
        }
      ],
      "parkingListings": [
        {
          "lot": "29",
          "price": 41
        }
      ],
      "parkingPrice": 41
    },
    "36": {
      "id": 36,
      "label": "Thu, Sep 24, 2026 · 7:15 PM · vs Reds",
      "url": "https://www.stubhub.com/atlanta-braves-atlanta-tickets-9-24-2026/event/159262179/",
      "listings": [
        {
          "section": "13",
          "row": "3",
          "price": 190
        },
        {
          "section": "13",
          "row": "2",
          "price": 196
        },
        {
          "section": "14",
          "row": "5",
          "price": 205
        },
        {
          "section": "13",
          "row": "1",
          "price": 212
        },
        {
          "section": "14",
          "row": "2",
          "price": 226
        },
        {
          "section": "15",
          "row": "2",
          "price": 235
        },
        {
          "section": "14",
          "row": "1",
          "price": 243
        }
      ],
      "parkingListings": [
        {
          "lot": "29",
          "price": 57
        }
      ],
      "parkingPrice": 57
    }
  }
}